meeting_notes_utils/__init__.py
meeting_notes_utils/file_utils.py
meeting_notes_utils/search_meeting_notes.py
meeting_notes_utils-0.1.0.dist-info/AUTHORS.rst
meeting_notes_utils-0.1.0.dist-info/LICENSE
meeting_notes_utils-0.1.0.dist-info/METADATA
meeting_notes_utils-0.1.0.dist-info/WHEEL
meeting_notes_utils-0.1.0.dist-info/entry_points.txt
meeting_notes_utils-0.1.0.dist-info/top_level.txt
meeting_notes_utils-0.1.0.dist-info/RECORD
