Metadata-Version: 2.1
Name: meeting_notes_utils
Version: 0.1.0
Summary: Collection of utility Python scripts for facilitating tasks for meeting notes.
Home-page: https://github.com/jai-python3/meeting_notes_utils
Author: Jaideep Sundaram
Author-email: jai.python3@gmail.com
Keywords: meeting_notes_utils
Classifier: Development Status :: 2 - Pre-Alpha
Classifier: Intended Audience :: Developers
Classifier: Natural Language :: English
Classifier: Programming Language :: Python :: 3
Classifier: Programming Language :: Python :: 3.6
Classifier: Programming Language :: Python :: 3.7
Classifier: Programming Language :: Python :: 3.8
Requires-Python: >=3.6
License-File: LICENSE
License-File: AUTHORS.rst
Requires-Dist: Click >=7.0
Requires-Dist: Rich
Requires-Dist: PyYAML
